{
    "build_hash": "98a92f16581df2e54004778544acfd718c486f72",
    "deleted_api_endpoints": [],
    "deleted_experiments": [],
    "extractor_version": 11,
    "modified_api_endpoints": [],
    "modified_experiments": [],
    "new_api_endpoints": [],
    "new_experiments": [],
    "string_changes": {
        "en": {
            "added": {},
            "deleted": {},
            "modified": {}
        },
        "ko": {
            "added": {},
            "deleted": {},
            "modified": {}
        }
    },
    "timestamp": "2026-05-15T20:47:59.380996+00:00"
}