{
    "build_hash": "8cf84c70e1673bd2381f7bf7f303286448a54d11",
    "deleted_api_endpoints": [],
    "deleted_experiments": [],
    "extractor_version": 11,
    "modified_api_endpoints": [],
    "modified_experiments": [],
    "new_api_endpoints": [],
    "new_experiments": [],
    "string_changes": {
        "en": {
            "added": {},
            "deleted": {},
            "modified": {}
        },
        "ko": {
            "added": {},
            "deleted": {},
            "modified": {}
        }
    },
    "timestamp": "2026-05-22T21:49:40.192474+00:00"
}