{
    "build_hash": "ddef244cff0dd2d91dff71bf1a5c6f84928ca9df",
    "deleted_api_endpoints": [],
    "deleted_experiments": [],
    "extractor_version": 11,
    "modified_api_endpoints": [],
    "modified_experiments": [],
    "new_api_endpoints": [],
    "new_experiments": [],
    "string_changes": {
        "en": {
            "added": {
                "UQ53sj": "{emojiName}, status emoji",
                "XFIqyk": "Color {hex}"
            },
            "deleted": {},
            "modified": {}
        },
        "ko": {
            "added": {},
            "deleted": {},
            "modified": {}
        }
    },
    "timestamp": "2026-05-14T06:58:58.224138+00:00"
}