{
    "build_hash": "490a8dc58484aaa2ff3ed74cdbe0af176498cd4d",
    "deleted_api_endpoints": [],
    "deleted_experiments": [],
    "extractor_version": 10,
    "modified_api_endpoints": [],
    "modified_experiments": [],
    "new_api_endpoints": [],
    "new_experiments": [],
    "string_changes": {
        "en": {
            "added": {},
            "deleted": {},
            "modified": {}
        },
        "ko": {
            "added": {},
            "deleted": {},
            "modified": {}
        }
    },
    "timestamp": "2026-05-08T20:05:31.870297+00:00"
}