{
    "build_hash": "e0e515401a86d7c115848a09256fc2fd21079430",
    "deleted_api_endpoints": [],
    "deleted_experiments": [],
    "extractor_version": 4,
    "modified_api_endpoints": [],
    "modified_experiments": [],
    "new_api_endpoints": [],
    "new_experiments": [],
    "string_changes": {
        "en": {
            "added": {
                "hFWVZQ": "Speaking indicators"
            },
            "deleted": {},
            "modified": {}
        },
        "ko": {
            "added": {},
            "deleted": {},
            "modified": {}
        }
    },
    "timestamp": "2026-05-01T18:02:00.657437+00:00"
}